strive/__init__.py
strive/reranker.py
strive/resources/en_stopwords.pkl
strive/resources/lid.176.ftz
strive/resources/pt_stopwords.pkl
strive/resources/nltk_data/corpora/stopwords.zip
strive/resources/nltk_data/corpora/wordnet.zip
strive/resources/nltk_data/corpora/words.zip
strive/resources/nltk_data/corpora/stopwords/README
strive/resources/nltk_data/corpora/stopwords/albanian
strive/resources/nltk_data/corpora/stopwords/arabic
strive/resources/nltk_data/corpora/stopwords/azerbaijani
strive/resources/nltk_data/corpora/stopwords/basque
strive/resources/nltk_data/corpora/stopwords/belarusian
strive/resources/nltk_data/corpora/stopwords/bengali
strive/resources/nltk_data/corpora/stopwords/catalan
strive/resources/nltk_data/corpora/stopwords/chinese
strive/resources/nltk_data/corpora/stopwords/danish
strive/resources/nltk_data/corpora/stopwords/dutch
strive/resources/nltk_data/corpora/stopwords/english
strive/resources/nltk_data/corpora/stopwords/finnish
strive/resources/nltk_data/corpora/stopwords/french
strive/resources/nltk_data/corpora/stopwords/german
strive/resources/nltk_data/corpora/stopwords/greek
strive/resources/nltk_data/corpora/stopwords/hebrew
strive/resources/nltk_data/corpora/stopwords/hinglish
strive/resources/nltk_data/corpora/stopwords/hungarian
strive/resources/nltk_data/corpora/stopwords/indonesian
strive/resources/nltk_data/corpora/stopwords/italian
strive/resources/nltk_data/corpora/stopwords/kazakh
strive/resources/nltk_data/corpora/stopwords/nepali
strive/resources/nltk_data/corpora/stopwords/norwegian
strive/resources/nltk_data/corpora/stopwords/portuguese
strive/resources/nltk_data/corpora/stopwords/romanian
strive/resources/nltk_data/corpora/stopwords/russian
strive/resources/nltk_data/corpora/stopwords/slovene
strive/resources/nltk_data/corpora/stopwords/spanish
strive/resources/nltk_data/corpora/stopwords/swedish
strive/resources/nltk_data/corpora/stopwords/tajik
strive/resources/nltk_data/corpora/stopwords/tamil
strive_ranker-2.35.dist-info/licenses/LICENSE
strive_ranker-2.35.dist-info/METADATA
strive_ranker-2.35.dist-info/WHEEL
strive_ranker-2.35.dist-info/top_level.txt
strive_ranker-2.35.dist-info/RECORD
