Metadata-Version: 2.4
Name: strive_ranker
Version: 2.35
Author: Carlo Moro
Author-email: Carlo Moro <cnmoro@gmail.com>
Classifier: Programming Language :: Python :: 3
Classifier: License :: OSI Approved :: MIT License
Classifier: Operating System :: OS Independent
Requires-Python: >=3.7
License-File: LICENSE
Requires-Dist: numpy<2
Requires-Dist: nltk
Requires-Dist: scikit-learn
Requires-Dist: fasttext
Requires-Dist: model2vec
Requires-Dist: faiss-cpu
Requires-Dist: bm25s
Dynamic: author
Dynamic: license-file
Dynamic: requires-python
